{"appointments":[{"date":"2021-10-29","schedule":"08:00","address":"Rua C++","phoneNumber":"55532121","name":"Maria Antônia dos Santos","CPF":"87667865466","genre":"Feminino","type":"Clareamento"},{"date":"2021-10-29","schedule":"09:00","address":"Rua Java","phoneNumber":"88876576","name":"João Oliveira","CPF":"09898787655","genre":"Maculino","type":"Limpeza"},{"date":"2021-10-27","schedule":"10:00","address":"Rua Cortiço","phoneNumber":"99987676","name":"Bertoleza Pontes","CPF":"67557698788","genre":"Feminino","type":"Clareamento"}]}